easter/__init__.py
easter/consumer.py
easter/dispatcher.py
easter/mailbox.py
easter/message.py
easter/rabbitmq/__init__.py
easter/rabbitmq/rabbitmq_connection_factory.py
easter/rabbitmq/rabbitmq_consumer.py
easter/rabbitmq/rabbitmq_dispatcher.py
easter/rabbitmq/factories/queue_collection_factory.py
easter/rabbitmq/factories/queue_exchange_factory.py
easter/rabbitmq/factories/queue_factory.py
easter-0.0.5.dist-info/licenses/LICENSE
easter-0.0.5.dist-info/METADATA
easter-0.0.5.dist-info/WHEEL
easter-0.0.5.dist-info/top_level.txt
easter-0.0.5.dist-info/RECORD
