Metadata-Version: 2.4
Name: easter
Version: 0.0.5
Summary: High-level communication between services using a RabbitMQ broker
Requires-Python: >=3.9
License-File: LICENSE
Requires-Dist: pika
Requires-Dist: jsonpickle
Dynamic: license-file
